redditreplier/redditreplier.py
redditreplier/__init__.py
redditreplier-1.0.1rc1.dist-info/METADATA
redditreplier-1.0.1rc1.dist-info/metadata.json
redditreplier-1.0.1rc1.dist-info/DESCRIPTION.rst
redditreplier-1.0.1rc1.dist-info/top_level.txt
redditreplier-1.0.1rc1.dist-info/WHEEL
redditreplier-1.0.1rc1.dist-info/RECORD
