Metadata-Version: 2.0
Name: redditreplier
Version: 1.0.1rc1
Summary: Create Reddit Bots
Home-page: https://github.com/naiyt/reddit-replier
Author: Nate Collings
Author-email: nate@natecollings.com
License: MIT
Keywords: reddit bots automation praw
Platform: UNKNOWN
Classifier: Development Status :: 3 - Alpha
Classifier: Intended Audience :: Developers
Classifier: Topic :: Software Development :: Build Tools
Classifier: License :: OSI Approved :: MIT License
Classifier: Programming Language :: Python :: 3
Classifier: Programming Language :: Python :: 3.2
Classifier: Programming Language :: Python :: 3.3
Classifier: Programming Language :: Python :: 3.4
Requires-Dist: praw
